.hgignore
CHANGES.txt
LICENSE.txt
README.txt
bootstrap.py
buildout.cfg
setup.py
js/__init__.py
js.foutbgone.egg-info/PKG-INFO
js.foutbgone.egg-info/SOURCES.txt
js.foutbgone.egg-info/dependency_links.txt
js.foutbgone.egg-info/entry_points.txt
js.foutbgone.egg-info/namespace_packages.txt
js.foutbgone.egg-info/not-zip-safe
js.foutbgone.egg-info/requires.txt
js.foutbgone.egg-info/top_level.txt
js/foutbgone/__init__.py
js/foutbgone/test_fout-b-gone.txt
js/foutbgone/resources/foutbgone.js
js/foutbgone/resources/foutbgone_init.js