Metadata-Version: 1.0
Name: js.foutbgone
Version: 0.1
Summary: Fanstatic packaging of FOUT-B-Gone
Home-page: UNKNOWN
Author: Fanstatic Developers
Author-email: fanstatic@googlegroups.com
License: BSD
Platform: UNKNOWN
